[{"test_id": 137, "simulation_file": "C:\\Users\\DmytroHUMENIUK\\Documents\\POLY\\cps-tool-competition\\results\\src.wogan_WOGAN_171146495869.0\\test.0137.json", "oob_side": "RIGHT", "direction_coverage": 0.38461538461538464, "maximum_curvature": 0.061748962496455936, "stdev_steering": 83.73253685428244, "mean_lateral_position": 1.0804316422585494, "max_lateral_position": 1.9954726372865288}, {"test_id": 146, "simulation_file": "C:\\Users\\DmytroHUMENIUK\\Documents\\POLY\\cps-tool-competition\\results\\src.wogan_WOGAN_171146495869.0\\test.0146.json", "oob_side": "RIGHT", "direction_coverage": 0.23076923076923078, "maximum_curvature": 0.06753340798982665, "stdev_steering": 25.205621164414758, "mean_lateral_position": -0.1286395195400391, "max_lateral_position": 1.4191279064960294}, {"test_id": 161, "simulation_file": "C:\\Users\\DmytroHUMENIUK\\Documents\\POLY\\cps-tool-competition\\results\\src.wogan_WOGAN_171146495869.0\\test.0161.json", "oob_side": "RIGHT", "direction_coverage": 0.34615384615384615, "maximum_curvature": 0.05872666608450227, "stdev_steering": 45.44867829079235, "mean_lateral_position": 0.5903811703135821, "max_lateral_position": 1.9538460147696262}, {"test_id": 195, "simulation_file": "C:\\Users\\DmytroHUMENIUK\\Documents\\POLY\\cps-tool-competition\\results\\src.wogan_WOGAN_171146495869.0\\test.0195.json", "oob_side": "RIGHT", "direction_coverage": 0.15384615384615385, "maximum_curvature": 0.06648559104749532, "stdev_steering": 91.41779410993776, "mean_lateral_position": 1.4602928868085234, "max_lateral_position": 1.890572405335566}, {"test_id": 249, "simulation_file": "C:\\Users\\DmytroHUMENIUK\\Documents\\POLY\\cps-tool-competition\\results\\src.wogan_WOGAN_171146495869.0\\test.0249.json", "oob_side": "RIGHT", "direction_coverage": 0.2692307692307692, "maximum_curvature": 0.06281530234351242, "stdev_steering": 29.743488739416154, "mean_lateral_position": -0.18413245992335522, "max_lateral_position": 0.4519085635309483}, {"test_id": 322, "simulation_file": "C:\\Users\\DmytroHUMENIUK\\Documents\\POLY\\cps-tool-competition\\results\\src.wogan_WOGAN_171146495869.0\\test.0322.json", "oob_side": "RIGHT", "direction_coverage": 0.3076923076923077, "maximum_curvature": 0.0656716048608503, "stdev_steering": 34.48370926552929, "mean_lateral_position": 1.3188947515317804, "max_lateral_position": 1.9982450922380235}, {"test_id": 327, "simulation_file": "C:\\Users\\DmytroHUMENIUK\\Documents\\POLY\\cps-tool-competition\\results\\src.wogan_WOGAN_171146495869.0\\test.0327.json", "oob_side": "RIGHT", "direction_coverage": 0.2692307692307692, "maximum_curvature": 0.06276236122918528, "stdev_steering": 36.10272926416706, "mean_lateral_position": 0.7025757533310792, "max_lateral_position": 1.944540018593662}, {"test_id": 347, "simulation_file": "C:\\Users\\DmytroHUMENIUK\\Documents\\POLY\\cps-tool-competition\\results\\src.wogan_WOGAN_171146495869.0\\test.0347.json", "oob_side": "RIGHT", "direction_coverage": 0.23076923076923078, "maximum_curvature": 0.06751823626005349, "stdev_steering": 49.93726259616132, "mean_lateral_position": 1.6334426368069548, "max_lateral_position": 1.9842553705611414}, {"test_id": 357, "simulation_file": "C:\\Users\\DmytroHUMENIUK\\Documents\\POLY\\cps-tool-competition\\results\\src.wogan_WOGAN_171146495869.0\\test.0357.json", "oob_side": "RIGHT", "direction_coverage": 0.34615384615384615, "maximum_curvature": 0.05982025980345276, "stdev_steering": 42.61510083080861, "mean_lateral_position": 0.39947914340829654, "max_lateral_position": 1.8784089874560876}, {"test_id": 361, "simulation_file": "C:\\Users\\DmytroHUMENIUK\\Documents\\POLY\\cps-tool-competition\\results\\src.wogan_WOGAN_171146495869.0\\test.0361.json", "oob_side": "RIGHT", "direction_coverage": 0.23076923076923078, "maximum_curvature": 0.06495877509060105, "stdev_steering": 52.020221528204395, "mean_lateral_position": 1.277020992567811, "max_lateral_position": 1.9970944208498618}, {"test_id": 363, "simulation_file": "C:\\Users\\DmytroHUMENIUK\\Documents\\POLY\\cps-tool-competition\\results\\src.wogan_WOGAN_171146495869.0\\test.0363.json", "oob_side": "RIGHT", "direction_coverage": 0.2692307692307692, "maximum_curvature": 0.0598054183045833, "stdev_steering": 41.30633941415957, "mean_lateral_position": 1.2163126703528027, "max_lateral_position": 1.966905161195277}, {"test_id": 365, "simulation_file": "C:\\Users\\DmytroHUMENIUK\\Documents\\POLY\\cps-tool-competition\\results\\src.wogan_WOGAN_171146495869.0\\test.0365.json", "oob_side": "RIGHT", "direction_coverage": 0.2692307692307692, "maximum_curvature": 0.06887942407020667, "stdev_steering": 72.46646185550186, "mean_lateral_position": 0.7171855241143943, "max_lateral_position": 1.8488683060652853}, {"test_id": 374, "simulation_file": "C:\\Users\\DmytroHUMENIUK\\Documents\\POLY\\cps-tool-competition\\results\\src.wogan_WOGAN_171146495869.0\\test.0374.json", "oob_side": "RIGHT", "direction_coverage": 0.3076923076923077, "maximum_curvature": 0.05145847419483351, "stdev_steering": 50.3074569132192, "mean_lateral_position": 1.2135919384319036, "max_lateral_position": 1.9964806817786833}, {"test_id": 403, "simulation_file": "C:\\Users\\DmytroHUMENIUK\\Documents\\POLY\\cps-tool-competition\\results\\src.wogan_WOGAN_171146495869.0\\test.0403.json", "oob_side": "RIGHT", "direction_coverage": 0.3076923076923077, "maximum_curvature": 0.06752008141769225, "stdev_steering": 30.488035810210064, "mean_lateral_position": 1.2899564750174983, "max_lateral_position": 1.9969011209813103}, {"test_id": 416, "simulation_file": "C:\\Users\\DmytroHUMENIUK\\Documents\\POLY\\cps-tool-competition\\results\\src.wogan_WOGAN_171146495869.0\\test.0416.json", "oob_side": "RIGHT", "direction_coverage": 0.23076923076923078, "maximum_curvature": 0.05709051811802861, "stdev_steering": 16.09795501574453, "mean_lateral_position": 0.06599445311050181, "max_lateral_position": 0.9024964825573514}, {"test_id": 442, "simulation_file": "C:\\Users\\DmytroHUMENIUK\\Documents\\POLY\\cps-tool-competition\\results\\src.wogan_WOGAN_171146495869.0\\test.0442.json", "oob_side": "RIGHT", "direction_coverage": 0.3076923076923077, "maximum_curvature": 0.06424435708065973, "stdev_steering": 58.492996742916844, "mean_lateral_position": 0.41093613170074583, "max_lateral_position": 1.9570005142835094}, {"test_id": 447, "simulation_file": "C:\\Users\\DmytroHUMENIUK\\Documents\\POLY\\cps-tool-competition\\results\\src.wogan_WOGAN_171146495869.0\\test.0447.json", "oob_side": "RIGHT", "direction_coverage": 0.2692307692307692, "maximum_curvature": 0.058593837102153656, "stdev_steering": 56.63926154864155, "mean_lateral_position": 0.598557074712893, "max_lateral_position": 1.9660941382317514}]